{
  "F0semitoneFrom27.5Hz_sma3nz_amean": "Pitch in semitones above 27.5hz  average over time",
  "F0semitoneFrom27.5Hz_sma3nz_stddevNorm": "Pitch in semitones above 27.5hz  relative standard deviation",
  "F0semitoneFrom27.5Hz_sma3nz_percentile20.0": "Pitch in semitones above 27.5hz  20th percentile (low value)",
  "F0semitoneFrom27.5Hz_sma3nz_percentile50.0": "Pitch in semitones above 27.5hz  median",
  "F0semitoneFrom27.5Hz_sma3nz_percentile80.0": "Pitch in semitones above 27.5hz  80th percentile (high value)",
  "F0semitoneFrom27.5Hz_sma3nz_pctlrange0-2": "Pitch in semitones above 27.5hz  variation in the lowest 2% range",
  "F0semitoneFrom27.5Hz_sma3nz_meanRisingSlope": "Pitch in semitones above 27.5hz  meanrisingslope",
  "F0semitoneFrom27.5Hz_sma3nz_stddevRisingSlope": "Pitch in semitones above 27.5hz  standard deviationrisingslope",
  "F0semitoneFrom27.5Hz_sma3nz_meanFallingSlope": "Pitch in semitones above 27.5hz  meanfallingslope",
  "F0semitoneFrom27.5Hz_sma3nz_stddevFallingSlope": "Pitch in semitones above 27.5hz  standard deviationfallingslope",
  "loudness_sma3_amean": "Perceived loudness  average over time",
  "loudness_sma3_stddevNorm": "Perceived loudness  relative standard deviation",
  "loudness_sma3_percentile20.0": "Perceived loudness  20th percentile (low value)",
  "loudness_sma3_percentile50.0": "Perceived loudness  median",
  "loudness_sma3_percentile80.0": "Perceived loudness  80th percentile (high value)",
  "loudness_sma3_pctlrange0-2": "Perceived loudness  variation in the lowest 2% range",
  "loudness_sma3_meanRisingSlope": "Perceived loudness  meanrisingslope",
  "loudness_sma3_stddevRisingSlope": "Perceived loudness  standard deviationrisingslope",
  "loudness_sma3_meanFallingSlope": "Perceived loudness  meanfallingslope",
  "loudness_sma3_stddevFallingSlope": "Perceived loudness  standard deviationfallingslope",
  "spectralFlux_sma3_amean": "Changes in spectral energy (spectral flux)  average over time",
  "spectralFlux_sma3_stddevNorm": "Changes in spectral energy (spectral flux)  relative standard deviation",
  "mfcc1_sma3_amean": "Mel\u2013frequency cepstral coefficient (mfcc) 1  average over time",
  "mfcc1_sma3_stddevNorm": "Mel\u2013frequency cepstral coefficient (mfcc) 1  relative standard deviation",
  "mfcc2_sma3_amean": "Mel\u2013frequency cepstral coefficient (mfcc) 2  average over time",
  "mfcc2_sma3_stddevNorm": "Mel\u2013frequency cepstral coefficient (mfcc) 2  relative standard deviation",
  "mfcc3_sma3_amean": "Mel\u2013frequency cepstral coefficient (mfcc) 3  average over time",
  "mfcc3_sma3_stddevNorm": "Mel\u2013frequency cepstral coefficient (mfcc) 3  relative standard deviation",
  "mfcc4_sma3_amean": "Mel\u2013frequency cepstral coefficient (mfcc) 4  average over time",
  "mfcc4_sma3_stddevNorm": "Mel\u2013frequency cepstral coefficient (mfcc) 4  relative standard deviation",
  "jitterLocal_sma3nz_amean": "Voice frequency instability (jitter)  average over time",
  "jitterLocal_sma3nz_stddevNorm": "Voice frequency instability (jitter)  relative standard deviation",
  "shimmerLocaldB_sma3nz_amean": "Voice amplitude instability (shimmer)  average over time",
  "shimmerLocaldB_sma3nz_stddevNorm": "Voice amplitude instability (shimmer)  relative standard deviation",
  "HNRdBACF_sma3nz_amean": "Clarity of voiced sound (hnr, db acf)  average over time",
  "HNRdBACF_sma3nz_stddevNorm": "Clarity of voiced sound (hnr, db acf)  relative standard deviation",
  "logRelF0-H1-H2_sma3nz_amean": "Relative strength of first two harmonics (h1\u2013h2)  average over time",
  "logRelF0-H1-H2_sma3nz_stddevNorm": "Relative strength of first two harmonics (h1\u2013h2)  relative standard deviation",
  "logRelF0-H1-A3_sma3nz_amean": "Relative strength of h1 to a3 harmonic  average over time",
  "logRelF0-H1-A3_sma3nz_stddevNorm": "Relative strength of h1 to a3 harmonic  relative standard deviation",
  "F1frequency_sma3nz_amean": "F1frequency  average over time",
  "F1frequency_sma3nz_stddevNorm": "F1frequency  relative standard deviation",
  "F1bandwidth_sma3nz_amean": "F1bandwidth  average over time",
  "F1bandwidth_sma3nz_stddevNorm": "F1bandwidth  relative standard deviation",
  "F1amplitudeLogRelF0_sma3nz_amean": "F1amplitude relative to pitch (log scale)  average over time",
  "F1amplitudeLogRelF0_sma3nz_stddevNorm": "F1amplitude relative to pitch (log scale)  relative standard deviation",
  "F2frequency_sma3nz_amean": "F2frequency  average over time",
  "F2frequency_sma3nz_stddevNorm": "F2frequency  relative standard deviation",
  "F2bandwidth_sma3nz_amean": "F2bandwidth  average over time",
  "F2bandwidth_sma3nz_stddevNorm": "F2bandwidth  relative standard deviation",
  "F2amplitudeLogRelF0_sma3nz_amean": "F2amplitude relative to pitch (log scale)  average over time",
  "F2amplitudeLogRelF0_sma3nz_stddevNorm": "F2amplitude relative to pitch (log scale)  relative standard deviation",
  "F3frequency_sma3nz_amean": "F3frequency  average over time",
  "F3frequency_sma3nz_stddevNorm": "F3frequency  relative standard deviation",
  "F3bandwidth_sma3nz_amean": "F3bandwidth  average over time",
  "F3bandwidth_sma3nz_stddevNorm": "F3bandwidth  relative standard deviation",
  "F3amplitudeLogRelF0_sma3nz_amean": "F3amplitude relative to pitch (log scale)  average over time",
  "F3amplitudeLogRelF0_sma3nz_stddevNorm": "F3amplitude relative to pitch (log scale)  relative standard deviation",
  "alphaRatioV_sma3nz_amean": "Balance of high vs. low frequencies (alpha ratio)v  average over time",
  "alphaRatioV_sma3nz_stddevNorm": "Balance of high vs. low frequencies (alpha ratio)v  relative standard deviation",
  "hammarbergIndexV_sma3nz_amean": "Spectral energy balance (hammarberg index)v  average over time",
  "hammarbergIndexV_sma3nz_stddevNorm": "Spectral energy balance (hammarberg index)v  relative standard deviation",
  "slopeV0-500_sma3nz_amean": "Spectral slopev0\u2013500  average over time",
  "slopeV0-500_sma3nz_stddevNorm": "Spectral slopev0\u2013500  relative standard deviation",
  "slopeV500-1500_sma3nz_amean": "Spectral slopev500\u20131500  average over time",
  "slopeV500-1500_sma3nz_stddevNorm": "Spectral slopev500\u20131500  relative standard deviation",
  "spectralFluxV_sma3nz_amean": "Changes in spectral energy (spectral flux)v  average over time",
  "spectralFluxV_sma3nz_stddevNorm": "Changes in spectral energy (spectral flux)v  relative standard deviation",
  "mfcc1V_sma3nz_amean": "Mel\u2013frequency cepstral coefficient (mfcc) 1v  average over time",
  "mfcc1V_sma3nz_stddevNorm": "Mel\u2013frequency cepstral coefficient (mfcc) 1v  relative standard deviation",
  "mfcc2V_sma3nz_amean": "Mel\u2013frequency cepstral coefficient (mfcc) 2v  average over time",
  "mfcc2V_sma3nz_stddevNorm": "Mel\u2013frequency cepstral coefficient (mfcc) 2v  relative standard deviation",
  "mfcc3V_sma3nz_amean": "Mel\u2013frequency cepstral coefficient (mfcc) 3v  average over time",
  "mfcc3V_sma3nz_stddevNorm": "Mel\u2013frequency cepstral coefficient (mfcc) 3v  relative standard deviation",
  "mfcc4V_sma3nz_amean": "Mel\u2013frequency cepstral coefficient (mfcc) 4v  average over time",
  "mfcc4V_sma3nz_stddevNorm": "Mel\u2013frequency cepstral coefficient (mfcc) 4v  relative standard deviation",
  "alphaRatioUV_sma3nz_amean": "Balance of high vs. low frequencies (alpha ratio)uv  average over time",
  "hammarbergIndexUV_sma3nz_amean": "Spectral energy balance (hammarberg index)uv  average over time",
  "slopeUV0-500_sma3nz_amean": "Spectral slopeuv0\u2013500  average over time",
  "slopeUV500-1500_sma3nz_amean": "Spectral slopeuv500\u20131500  average over time",
  "spectralFluxUV_sma3nz_amean": "Changes in spectral energy (spectral flux)uv  average over time",
  "loudnessPeaksPerSec": "Perceived loudnesspeakspersec",
  "VoicedSegmentsPerSec": "Voicedsegmentspersec",
  "MeanVoicedSegmentLengthSec": "Meanvoicedsegmentlengthsec",
  "StddevVoicedSegmentLengthSec": "Stddevvoicedsegmentlengthsec",
  "MeanUnvoicedSegmentLength": "Meanunvoicedsegmentlength",
  "StddevUnvoicedSegmentLength": "Stddevunvoicedsegmentlength",
  "equivalentSoundLevel_dBp": "Equivalentsoundlevel dbp"
}